pysubyt/__init__.py
pysubyt/__main__.py
pysubyt/__version__.py
pysubyt/api.py
pysubyt/j2/__init__.py
pysubyt/j2/generator.py
pysubyt/sinks.py
pysubyt/sources.py
pysubyt/subyt.py
pysubyt-0.1.0.dist-info/entry_points.txt
pysubyt-0.1.0.dist-info/LICENSE
pysubyt-0.1.0.dist-info/METADATA
pysubyt-0.1.0.dist-info/WHEEL
pysubyt-0.1.0.dist-info/RECORD
