Metadata-Version: 2.1
Name: pysubyt
Version: 0.1.0
Summary: Python implementation of LinkedData Templates to produce triples out of various datasources
Home-page: https://github.com/vliz-be-opsci/pysubyt
License: MIT
Author: Marc Portier
Author-email: marc.portier@gmail.com
Requires-Python: >=3.9,<4.0
Classifier: License :: OSI Approved :: MIT License
Classifier: Programming Language :: Python
Classifier: Programming Language :: Python :: 3
Classifier: Programming Language :: Python :: 3.9
Classifier: Programming Language :: Python :: 3.10
Classifier: Programming Language :: Python :: 3.11
Requires-Dist: furo
Requires-Dist: jinja2
Requires-Dist: pandas
Requires-Dist: pyrdfj2
Requires-Dist: python-dateutil
Requires-Dist: recommonmark
Requires-Dist: requests
Requires-Dist: typeguard
Requires-Dist: uritemplate
Requires-Dist: validators
Requires-Dist: xmlasdict
Project-URL: Repository, https://github.com/vliz-be-opsci/pysubyt
